hmp/__init__.py
hmp/_version.py
hmp/experimental.py
hmp/loocv.py
hmp/mcca.py
hmp/models.py
hmp/simulations.py
hmp/utils.py
hmp/visu.py
hmp-0.5.0.dist-info/LICENSE.md
hmp-0.5.0.dist-info/METADATA
hmp-0.5.0.dist-info/WHEEL
hmp-0.5.0.dist-info/top_level.txt
hmp-0.5.0.dist-info/RECORD
