Metadata-Version: 2.1
Name: hmp
Version: 0.5.0
Summary: Package for fitting Hidden Multivariate pattern model to time-series
Author-email: Gabriel Weindel <gabriel.weindel@gmail.com>, Leendert van Maanen <e@mail.com>, Jelmer Borst <e@mail.com>
License: BSD 3-Clause License
Project-URL: Homepage, https://github.com/GWeindel/hmp
Project-URL: Bug Tracker, https://github.com/GWeindel/hmp/issues
Keywords: neuroscience,neuroimaging,MEG,EEG,ECoG,brain
Classifier: Programming Language :: Python :: 3
Classifier: Operating System :: OS Independent
Classifier: Intended Audience :: Science/Research
Classifier: Intended Audience :: Developers
Classifier: Programming Language :: Python
Classifier: Topic :: Software Development
Classifier: Topic :: Scientific/Engineering
Obsoletes: hsmm_mvpy
Requires-Python: >=3.10
License-File: LICENSE.md
Requires-Dist: mne>=1.0.0
Requires-Dist: numpy
Requires-Dist: xarray>=2023.8.0
Requires-Dist: scikit-learn
Requires-Dist: statsmodels
Requires-Dist: scipy
Requires-Dist: netcdf4
Requires-Dist: more_itertools
Requires-Dist: ipywidgets
Requires-Dist: nibabel
Provides-Extra: test
Requires-Dist: pytest; extra == "test"
